setup.cfg
setup.py
blitzr/__init__.py
blitzr/client.py
blitzr/exceptions.py
blitzr.egg-info/PKG-INFO
blitzr.egg-info/SOURCES.txt
blitzr.egg-info/dependency_links.txt
blitzr.egg-info/not-zip-safe
blitzr.egg-info/requires.txt
blitzr.egg-info/top_level.txt