Metadata-Version: 1.0
Name: blitzr
Version: 1.1.2
Summary: Blitzr Python Client
Home-page: https://github.com/blitzr/blitzr-python
Author: Blitzr
Author-email: contact@blitzr.com
License: UNKNOWN
Download-URL: https://github.com/blitzr/blitzr-python/tarball/1.1.2
Platform: UNKNOWN
